mcp_server_jetour0094766_deepresearch/__init__.py
mcp_server_jetour0094766_deepresearch/__main__.py
mcp_server_jetour0094766_deepresearch/server.py
mcp_server_jetour0094766_deepresearch-0.3.9.dist-info/METADATA
mcp_server_jetour0094766_deepresearch-0.3.9.dist-info/WHEEL
mcp_server_jetour0094766_deepresearch-0.3.9.dist-info/entry_points.txt
mcp_server_jetour0094766_deepresearch-0.3.9.dist-info/top_level.txt
mcp_server_jetour0094766_deepresearch-0.3.9.dist-info/RECORD
