Metadata-Version: 2.4
Name: mcp-server-jetour0094766-deepresearch
Version: 0.3.9
Summary: 捷途实现类deepresearch功能的MCP工具
Requires-Python: >=3.12
Requires-Dist: asyncio>=4.0.0
Requires-Dist: langchain-community>=0.3.27
Requires-Dist: langchain-core>=0.3.72
Requires-Dist: langchain-openai>=0.3.28
Requires-Dist: langgraph>=0.6.3
Requires-Dist: mcp>=1.12.3
Requires-Dist: nest-asyncio>=1.6.0
Requires-Dist: openai>=1.99.1
Requires-Dist: pydantic>=2.11.7
Requires-Dist: python-dotenv>=1.1.1
Requires-Dist: tavily-python>=0.3.0
